[
  {
    "email": "jakeemdund.pacificadorii-22@cpu.edu.ph",
    "orderId": "104414",
    "customerName": "Pacificador, Jake Edmund",
    "items": [
      {
        "name": "Lanyard",
        "quantity": 1,
        "price": 119,
        "discount": 0,
        "subtotal": 119
      }
    ],
    "total": 119,
    "paymentStatus": "Paid"
  },
  {
    "email": "shawnsevalair@gmail.com",
    "orderId": "709838",
    "customerName": "Alair, Shawn Khennee",
    "items": [
      {
        "name": "Lanyard",
        "quantity": 1,
        "price": 119,
        "discount": 0,
        "subtotal": 119
      }
    ],
    "total": 119,
    "paymentStatus": "Paid"
  },
  {
    "email": "marieantoinette.legayada-22@cpu.edu.ph",
    "orderId": "520322",
    "customerName": "Legayada, Marie Antoinette",
    "items": [
      {
        "name": "Lanyard",
        "quantity": 3,
        "price": 119,
        "discount": 0,
        "subtotal": 357
      }
    ],
    "total": 357,
    "paymentStatus": "Paid"
  },
  {
    "email": "naene30gust@gmail.com",
    "orderId": "705489",
    "customerName": "Tuden, Nelissa",
    "items": [
      {
        "name": "Lanyard",
        "quantity": 2,
        "price": 119,
        "discount": 0,
        "subtotal": 238
      }
    ],
    "total": 238,
    "paymentStatus": "Paid"
  },
  {
    "email": "amadafrancy1983@gmail.com",
    "orderId": "326289",
    "customerName": "Amada, Francy Angelo",
    "items": [
      {
        "name": "Lanyard",
        "quantity": 1,
        "price": 119,
        "discount": 0,
        "subtotal": 119
      }
    ],
    "total": 119,
    "paymentStatus": "Paid"
  },
  {
    "email": "ryanpaul.gabrillo-12@cpu.edu.ph",
    "orderId": "753847",
    "customerName": "Gabrillo, Ryan Paul",
    "items": [
      {
        "name": "Lanyard",
        "quantity": 1,
        "price": 119,
        "discount": 0,
        "subtotal": 119
      }
    ],
    "total": 119,
    "paymentStatus": "Paid"
  },
  {
    "email": "diademgrace.arroz-21@cpu.edu.ph",
    "orderId": "167244",
    "customerName": "Arroz, Diadem Grace",
    "items": [
      {
        "name": "Lanyard",
        "quantity": 1,
        "price": 119,
        "discount": 75,
        "subtotal": 29.75
      }
    ],
    "total": 29.75,
    "paymentStatus": "Paid"
  },
  {
    "email": "jaycellearianne.basco-21@cpu.edu.ph",
    "orderId": "101595",
    "customerName": "Basco, Jaycelle Arianne",
    "items": [
      {
        "name": "Lanyard",
        "quantity": 3,
        "price": 119,
        "discount": 0,
        "subtotal": 357
      }
    ],
    "total": 357,
    "paymentStatus": "Paid"
  },
  {
    "email": "jpp200214@gmail.com",
    "orderId": "475877",
    "customerName": "Pineda, John Patrick",
    "items": [
      {
        "name": "Lanyard",
        "quantity": 1,
        "price": 119,
        "discount": 0,
        "subtotal": 119
      }
    ],
    "total": 119,
    "paymentStatus": "Paid"
  },
  {
    "email": "ianclyde.tejada-16@cpu.edu.ph",
    "orderId": "699347",
    "customerName": "Tejada, Ian Clyde",
    "items": [
      {
        "name": "Lanyard",
        "quantity": 1,
        "price": 119,
        "discount": 0,
        "subtotal": 119
      }
    ],
    "total": 119,
    "paymentStatus": "Not Paid"
  },
  {
    "email": "davejhaeson.alivio-21@cpu.edu.ph",
    "orderId": "317436",
    "customerName": "Alivio, Dave Jhaeson",
    "items": [
      {
        "name": "Lanyard",
        "quantity": 1,
        "price": 119,
        "discount": 25,
        "subtotal": 89.25
      }
    ],
    "total": 89.25,
    "paymentStatus": "Paid"
  },
  {
    "email": "kyledominic.lomigo@gmail.com",
    "orderId": "853354",
    "customerName": "Lomigo, Kyle Dominic ",
    "items": [
      {
        "name": "Lanyard",
        "quantity": 1,
        "price": 119,
        "discount": 0,
        "subtotal": 119
      }
    ],
    "total": 119,
    "paymentStatus": "Paid"
  },
  {
    "email": "paulvincent.lerado-21@cpu.edu.ph",
    "orderId": "722261",
    "customerName": "Lerado, Paul Vincent ",
    "items": [
      {
        "name": "Lanyard",
        "quantity": 1,
        "price": 119,
        "discount": 0,
        "subtotal": 119
      }
    ],
    "total": 119,
    "paymentStatus": "Paid"
  },
  {
    "email": "faithninamarie.magsael-21@cpu.edu.ph",
    "orderId": "665107",
    "customerName": "Magsael, Faith Niña Marie",
    "items": [
      {
        "name": "Lanyard",
        "quantity": 1,
        "price": 119,
        "discount": 0,
        "subtotal": 119
      }
    ],
    "total": 119,
    "paymentStatus": "Paid"
  },
  {
    "email": "lovefaith.alcorin-11@cpu.edu.ph",
    "orderId": "396990",
    "customerName": "Alcorin, Love Faith H. ",
    "items": [
      {
        "name": "Lanyard",
        "quantity": 1,
        "price": 119,
        "discount": 25,
        "subtotal": 89.25
      }
    ],
    "total": 89.25,
    "paymentStatus": "Not Paid"
  },
  {
    "email": "amadafrancy1983@gmail.com",
    "orderId": "466934",
    "customerName": "Amada, Francy Angelo",
    "items": [
      {
        "name": "Lanyard",
        "quantity": 1,
        "price": 119,
        "discount": 0,
        "subtotal": 119
      }
    ],
    "total": 119,
    "paymentStatus": "Paid"
  },
  {
    "email": "shawnbarza414@gmail.com",
    "orderId": "182904",
    "customerName": "Barza, Shawn Timothy Ike ",
    "items": [
      {
        "name": "Lanyard",
        "quantity": 1,
        "price": 119,
        "discount": 0,
        "subtotal": 119
      }
    ],
    "total": 119,
    "paymentStatus": "Paid"
  },
  {
    "email": "rainechristine.perez-22@cpu.edu.ph",
    "orderId": "781494",
    "customerName": "Perez, Raine Christine ",
    "items": [
      {
        "name": "Lanyard",
        "quantity": 1,
        "price": 119,
        "discount": 25,
        "subtotal": 89.25
      }
    ],
    "total": 89.25,
    "paymentStatus": "Paid"
  },
  {
    "email": "paulandreiardiente@gmail.com",
    "orderId": "838224",
    "customerName": "Ardiente, Paul Andrei ",
    "items": [
      {
        "name": "Lanyard",
        "quantity": 1,
        "price": 119,
        "discount": 0,
        "subtotal": 119
      }
    ],
    "total": 119,
    "paymentStatus": "Paid"
  },
  {
    "email": "joshuademerin092503@gmail.com",
    "orderId": "264809",
    "customerName": "Demerin Joshua Ulimer",
    "items": [
      {
        "name": "Lanyard",
        "quantity": 1,
        "price": 119,
        "discount": 0,
        "subtotal": 119
      }
    ],
    "total": 119,
    "paymentStatus": "Paid"
  },
  {
    "email": "stevenballaret@gmail.com",
    "orderId": "715075",
    "customerName": "Ballaret, Steven",
    "items": [
      {
        "name": "Lanyard",
        "quantity": 1,
        "price": 119,
        "discount": 25,
        "subtotal": 89.25
      }
    ],
    "total": 89.25,
    "paymentStatus": "Paid"
  },
  {
    "email": "joevany.aliguinjr-22@cpu.edu.ph",
    "orderId": "453652",
    "customerName": "Aliguin, Joevany",
    "items": [
      {
        "name": "Lanyard",
        "quantity": 1,
        "price": 119,
        "discount": 0,
        "subtotal": 119
      }
    ],
    "total": 119,
    "paymentStatus": "Paid"
  },
  {
    "email": "mjconstantino12345@gmail.com",
    "orderId": "196808",
    "customerName": "Constantino, Michael Jay",
    "items": [
      {
        "name": "Lanyard",
        "quantity": 1,
        "price": 119,
        "discount": 0,
        "subtotal": 119
      }
    ],
    "total": 119,
    "paymentStatus": "Not Paid"
  },
  {
    "email": "kenjoel275@gmail.com",
    "orderId": "488543",
    "customerName": "Urbano, Kenneth Joel",
    "items": [
      {
        "name": "Lanyard",
        "quantity": 1,
        "price": 119,
        "discount": 0,
        "subtotal": 119
      }
    ],
    "total": 119,
    "paymentStatus": "Paid"
  },
  {
    "email": "josearronfranz.suoberon-23@cpu.edu.ph",
    "orderId": "531521",
    "customerName": "Suoberon, Jose Arron Franz",
    "items": [
      {
        "name": "Lanyard",
        "quantity": 1,
        "price": 119,
        "discount": 0,
        "subtotal": 119
      }
    ],
    "total": 119,
    "paymentStatus": "Paid"
  },
  {
    "email": "samenianjoshua@gmail.com",
    "orderId": "538354",
    "customerName": "Samenian, Joshua",
    "items": [
      {
        "name": "Lanyard",
        "quantity": 1,
        "price": 119,
        "discount": 0,
        "subtotal": 119
      }
    ],
    "total": 119,
    "paymentStatus": "Not Paid"
  },
  {
    "email": "nicholaesara16@gmail.com",
    "orderId": "421748",
    "customerName": "Sara, Nicholae",
    "items": [
      {
        "name": "Lanyard",
        "quantity": 1,
        "price": 119,
        "discount": 0,
        "subtotal": 119
      }
    ],
    "total": 119,
    "paymentStatus": "Paid"
  },
  {
    "email": "juliusreygabriel.parman-23@cpu.edu.ph",
    "orderId": "392578",
    "customerName": "Parman, Julius Rey Gabriel ",
    "items": [
      {
        "name": "Lanyard",
        "quantity": 1,
        "price": 119,
        "discount": 0,
        "subtotal": 119
      }
    ],
    "total": 119,
    "paymentStatus": "Paid"
  },
  {
    "email": "alhenajulienne.gedalanga-21@cpu.edu.ph",
    "orderId": "651989",
    "customerName": "Gedalanga, Alhena Julienne",
    "items": [
      {
        "name": "Lanyard",
        "quantity": 1,
        "price": 119,
        "discount": 100,
        "subtotal": 0
      }
    ],
    "total": 0,
    "paymentStatus": "Paid"
  },
  {
    "email": "danielmark.wiegand-17@cpu.edu.ph",
    "orderId": "187430",
    "customerName": "Wiegand, Daniel Mark ",
    "items": [
      {
        "name": "Lanyard",
        "quantity": 1,
        "price": 119,
        "discount": 25,
        "subtotal": 89.25
      }
    ],
    "total": 89.25,
    "paymentStatus": "Paid"
  },
  {
    "email": "chadandrada20@gmail.com",
    "orderId": "894710",
    "customerName": "Andrada, Chad Denard",
    "items": [
      {
        "name": "Lanyard",
        "quantity": 1,
        "price": 119,
        "discount": 0,
        "subtotal": 119
      }
    ],
    "total": 119,
    "paymentStatus": "Paid"
  },
  {
    "email": "seannamo15@gmail.com",
    "orderId": "301906",
    "customerName": "Namo, Sean Patrick",
    "items": [
      {
        "name": "Lanyard",
        "quantity": 1,
        "price": 119,
        "discount": 25,
        "subtotal": 89.25
      }
    ],
    "total": 89.25,
    "paymentStatus": "Paid"
  },
  {
    "email": "aljasonjavier@gmail.com",
    "orderId": "619143",
    "customerName": "Javier, Aljason ",
    "items": [
      {
        "name": "Lanyard",
        "quantity": 1,
        "price": 119,
        "discount": 0,
        "subtotal": 119
      }
    ],
    "total": 119,
    "paymentStatus": "Paid"
  },
  {
    "email": "yoshifumisuzuki81194@gmail.com",
    "orderId": "593002",
    "customerName": "Suzuki, Yoshifumi ",
    "items": [
      {
        "name": "Lanyard",
        "quantity": 1,
        "price": 119,
        "discount": 0,
        "subtotal": 119
      }
    ],
    "total": 119,
    "paymentStatus": "Paid"
  },
  {
    "email": "kassimmanaf@gmail.com",
    "orderId": "131693",
    "customerName": "Alonsagay, Lois",
    "items": [
      {
        "name": "Lanyard",
        "quantity": 5,
        "price": 119,
        "discount": 0,
        "subtotal": 595
      }
    ],
    "total": 595,
    "paymentStatus": "Not Paid"
  },
  {
    "email": "kaizensomosera.04@gmail.com",
    "orderId": "116639",
    "customerName": "Somosera, Kaizen Louie",
    "items": [
      {
        "name": "Lanyard",
        "quantity": 1,
        "price": 119,
        "discount": 0,
        "subtotal": 119
      }
    ],
    "total": 119,
    "paymentStatus": "Paid"
  },
  {
    "email": "jennyrosesuelan@gmail.com",
    "orderId": "272705",
    "customerName": "Suelan, Jenny Rose",
    "items": [
      {
        "name": "Lanyard",
        "quantity": 1,
        "price": 119,
        "discount": 0,
        "subtotal": 119
      }
    ],
    "total": 119,
    "paymentStatus": "Paid"
  },
  {
    "email": "cassandraysabel24@gmail.com",
    "orderId": "778437",
    "customerName": "Gallo, Cassandra Ysabel",
    "items": [
      {
        "name": "Lanyard",
        "quantity": 1,
        "price": 119,
        "discount": 25,
        "subtotal": 89.25
      }
    ],
    "total": 89.25,
    "paymentStatus": "Paid"
  },
  {
    "email": "sidryl.gerardo-21@cpu.edu.ph",
    "orderId": "997921",
    "customerName": "sidryl tana gerardo",
    "items": [
      {
        "name": "Lanyard",
        "quantity": 2,
        "price": 119,
        "discount": 25,
        "subtotal": 178.5
      }
    ],
    "total": 178.5,
    "paymentStatus": "Not Paid"
  },
  {
    "email": "dainzandrei.trasadas-23@cpu.edu.ph",
    "orderId": "773057",
    "customerName": "Trasadas, Dainz Andrei",
    "items": [
      {
        "name": "Lanyard",
        "quantity": 1,
        "price": 119,
        "discount": 0,
        "subtotal": 119
      }
    ],
    "total": 119,
    "paymentStatus": "Paid"
  },
  {
    "email": "elmorjohncortez97@gmail.com",
    "orderId": "920451",
    "customerName": "Cortez, Elmor John",
    "items": [
      {
        "name": "Lanyard",
        "quantity": 1,
        "price": 119,
        "discount": 0,
        "subtotal": 119
      }
    ],
    "total": 119,
    "paymentStatus": "Not Paid"
  },
  {
    "email": "jiverlee.delacruz-20@cpu.edu.ph",
    "orderId": "511034",
    "customerName": "Dela Cruz, Jiverlee",
    "items": [
      {
        "name": "Lanyard",
        "quantity": 1,
        "price": 119,
        "discount": 0,
        "subtotal": 119
      }
    ],
    "total": 119,
    "paymentStatus": "Not Paid"
  },
  {
    "email": "jp.rosalita-09@cpu.edu.ph",
    "orderId": "789858",
    "customerName": "Rosalita, JP",
    "items": [
      {
        "name": "Lanyard",
        "quantity": 1,
        "price": 119,
        "discount": 0,
        "subtotal": 119
      }
    ],
    "total": 119,
    "paymentStatus": "Paid"
  },
  {
    "email": "johnpatrick.gerona-17@cpu.edu.ph",
    "orderId": "673143",
    "customerName": "Gerona, John Patrick ",
    "items": [
      {
        "name": "Lanyard",
        "quantity": 2,
        "price": 119,
        "discount": 0,
        "subtotal": 238
      }
    ],
    "total": 238,
    "paymentStatus": "Paid"
  },
  {
    "orderId": "223280",
    "items": [
      {
        "name": "Lanyard",
        "quantity": null,
        "price": 119,
        "discount": 0,
        "subtotal": null
      }
    ],
    "total": null
  }
]